number_formatter.py
number_formatter-0.1.dist-info/METADATA
number_formatter-0.1.dist-info/WHEEL
number_formatter-0.1.dist-info/top_level.txt
number_formatter-0.1.dist-info/RECORD
