Metadata-Version: 2.1
Name: number_formatter
Version: 0.1
Summary: Add comma separation to your larger numbers!
Home-page: UNKNOWN
Author: SiXFeet
Author-email: chukunekunwanwene@gmail.com
License: UNKNOWN
Keywords: number formatter
Platform: UNKNOWN
Classifier: Programming Language :: Python :: 3
Classifier: License :: OSI Approved :: MIT License
Classifier: Operating System :: OS Independent
